cs2py/CSharpToPython.py
cs2py/__init__.py
cs2py-0.0.1.dist-info/METADATA
cs2py-0.0.1.dist-info/WHEEL
cs2py-0.0.1.dist-info/top_level.txt
cs2py-0.0.1.dist-info/RECORD
